MANIFEST.in
README.rst
setup.py
src/ofxstatement/__init__.py
src/ofxstatement/plugins/__init__.py
src/ofxstatement/plugins/fr/__init__.py
src/ofxstatement/plugins/fr/banquepostale.py
src/ofxstatement_fr_banquepostale.egg-info/PKG-INFO
src/ofxstatement_fr_banquepostale.egg-info/SOURCES.txt
src/ofxstatement_fr_banquepostale.egg-info/dependency_links.txt
src/ofxstatement_fr_banquepostale.egg-info/entry_points.txt
src/ofxstatement_fr_banquepostale.egg-info/namespace_packages.txt
src/ofxstatement_fr_banquepostale.egg-info/requires.txt
src/ofxstatement_fr_banquepostale.egg-info/top_level.txt
src/ofxstatement_fr_banquepostale.egg-info/zip-safe
src/tests/__init__.py
src/tests/test_banquepostale.py
src/tests/resources/__init__.py