Metadata-Version: 1.1
Name: ofxstatement-fr-banquepostale
Version: 0.0.1
Summary: ofxstatement plugin for La Banque Postale - France
Home-page: https://gitlab.com/crepi22/ofxstatement-fr-labanquepostale
Author: Pierre Cregut
Author-email: crepi22y@gmail.com
License: GPLv3
Keywords: ofx,banking,statement
Platform: UNKNOWN
Classifier: Development Status :: 3 - Alpha
Classifier: Programming Language :: Python :: 3
Classifier: Natural Language :: English
Classifier: Topic :: Office/Business :: Financial :: Accounting
Classifier: Topic :: Utilities
Classifier: Environment :: Console
Classifier: Operating System :: OS Independent
Classifier: License :: OSI Approved :: GNU General Public License v3 (GPLv3)
